samstatic_flask/__init__.py
samstatic_flask/app.py
samstatic_flask/config.py
samstatic_flask/ctx.py
samstatic_flask/helper.py
samstatic_flask/doc/LICENSE
samstatic_flask/doc/README.md
samstatic_flask-1.0.2.dist-info/LICENSE
samstatic_flask-1.0.2.dist-info/METADATA
samstatic_flask-1.0.2.dist-info/WHEEL
samstatic_flask-1.0.2.dist-info/top_level.txt
samstatic_flask-1.0.2.dist-info/RECORD
